{"code_basic_ubuntu.md":"CY8idrEY","code_database_index.md":"CL5z22vK","code_thinkphp_install.md":"83fZr9Vk","code_database_mysqltoduckdb.md":"BC-XBN1i","index.md":"CLjsyITG","code_database_duckdb.md":"DjBrEzIn","code_lang_js_arrayinstancemethod.md":"DLadzomK","code_vue3_vue3init.md":"HcHCWiEd","code_vue3_index.md":"WFz0P7ax","code_basic_multipass.md":"alEaSEpk","code_lang_js_index.md":"E_B4Swb2","code_basic_php.md":"C_yIRspW","code_lang_php_calcruntime.md":"Cw2rDtVa","code_basic_index.md":"CBM4pZtL","code_lang_php_index.md":"DnS2IxOr","code_database_duckdbfunction.md":"CuFRMF0Z","code_vue3_buildinfunction.md":"CYHm9IJi","code_basic_git.md":"Bv7Z8z0e","code_lang_php_formitemtomuch.md":"C3qpg_BU","code_vue3_vite.md":"DaQO4M3A","code_basic_bandwagonhost.md":"Csie7Jom","code_vue3_vscodeplug.md":"Qi0FKf_X","code_vue3_template.md":"DFrdO4Y0","code_basic_nodejs.md":"CtJO-_dT","code_datastruct_index.md":"uXbUJmOj","api-examples.md":"ByUnTqzh","markdown-examples.md":"Bck3DSID","code_lang_php_uploadfilelimit.md":"lETWv23t"}
